Metadata-Version: 2.1
Name: Task-12
Version: 0.1
Summary: this project is for testing
Home-page: https://github.com/LesyaEryuzheva/My_hometasks
Author: Eryuzheva Alesya
License: MIT
Platform: UNKNOWN
License-File: LICENSE.txt
